speedyapi/__init__.py
speedyapi/color.py
speedyapi/exceptions.py
speedyapi/handler.py
speedyapi/limiter.py
speedyapi/logging.py
speedyapi/main.py
speedyapi/parameters.py
speedyapi/respond.py
speedyapi/swagger.py
speedyapi/swagger_objects.py
speedyapi/tests.py
speedyapi/types.py
speedyapi/util.py
speedyapi-1.0.11.dist-info/METADATA
speedyapi-1.0.11.dist-info/WHEEL
speedyapi-1.0.11.dist-info/top_level.txt
speedyapi-1.0.11.dist-info/RECORD
