Metadata-Version: 2.1
Name: speedyapi
Version: 1.0.11
Summary: An easy to use Python module for creating API.
Author: CodingYuno
Project-URL: Source Code, https://github.com/CodingYuno/speedyapi/
Project-URL: Issue Tracker, https://github.com/CodingYuno/speedyapi/issues/
Classifier: Development Status :: 5 - Production/Stable
Classifier: Environment :: Web Environment
Classifier: Intended Audience :: Developers
Classifier: License :: OSI Approved :: MIT License
Classifier: Operating System :: OS Independent
Classifier: Programming Language :: Python :: 3
Classifier: Topic :: Software Development :: Libraries :: Application Frameworks
Requires-Python: >=3.10
Requires-Dist: flask[async] (>=2.2)
Requires-Dist: requests (>=2.9.2)
Requires-Dist: pygments
Provides-Extra: async
Requires-Dist: flask[async] ; extra == 'async'
